[
  {
    "brans": "ITA",
    "dersNo": "101",
    "terms": [
      {
        "dersNo": "101",
        "donemKodu": "201930",
        "yilAdi": "2018-2019",
        "donemTip": "Yaz Dönemi",
        "toplamOgrenci": 21,
        "dagilim": [
          {
            "HarfNotu": "AA",
            "Sayi": 6,
            "Yuzde": 28.57
          },
          {
            "HarfNotu": "BA+",
            "Sayi": 0,
            "Yuzde": 0.0
          },
          {
            "HarfNotu": "BA",
            "Sayi": 8,
            "Yuzde": 38.1
          },
          {
            "HarfNotu": "BB+",
            "Sayi": 0,
            "Yuzde": 0.0
          },
          {
            "HarfNotu": "BB",
            "Sayi": 3,
            "Yuzde": 14.29
          },
          {
            "HarfNotu": "CB+",
            "Sayi": 0,
            "Yuzde": 0.0
          },
          {
            "HarfNotu": "CB",
            "Sayi": 1,
            "Yuzde": 4.76
          },
          {
            "HarfNotu": "CC+",
            "Sayi": 0,
            "Yuzde": 0.0
          },
          {
            "HarfNotu": "CC",
            "Sayi": 1,
            "Yuzde": 4.76
          },
          {
            "HarfNotu": "DC+",
            "Sayi": 0,
            "Yuzde": 0.0
          },
          {
            "HarfNotu": "DC",
            "Sayi": 0,
            "Yuzde": 0.0
          },
          {
            "HarfNotu": "DD+",
            "Sayi": 0,
            "Yuzde": 0.0
          },
          {
            "HarfNotu": "DD",
            "Sayi": 0,
            "Yuzde": 0.0
          },
          {
            "HarfNotu": "FF",
            "Sayi": 2,
            "Yuzde": 9.52
          },
          {
            "HarfNotu": "VF",
            "Sayi": 0,
            "Yuzde": 0.0
          }
        ]
      },
      {
        "dersNo": "101",
        "donemKodu": "201920",
        "yilAdi": "2018-2019",
        "donemTip": "Bahar Dönemi",
        "toplamOgrenci": 119,
        "dagilim": [
          {
            "HarfNotu": "AA",
            "Sayi": 21,
            "Yuzde": 17.65
          },
          {
            "HarfNotu": "BA+",
            "Sayi": 0,
            "Yuzde": 0.0
          },
          {
            "HarfNotu": "BA",
            "Sayi": 32,
            "Yuzde": 26.89
          },
          {
            "HarfNotu": "BB+",
            "Sayi": 0,
            "Yuzde": 0.0
          },
          {
            "HarfNotu": "BB",
            "Sayi": 30,
            "Yuzde": 25.21
          },
          {
            "HarfNotu": "CB+",
            "Sayi": 0,
            "Yuzde": 0.0
          },
          {
            "HarfNotu": "CB",
            "Sayi": 15,
            "Yuzde": 12.61
          },
          {
            "HarfNotu": "CC+",
            "Sayi": 0,
            "Yuzde": 0.0
          },
          {
            "HarfNotu": "CC",
            "Sayi": 3,
            "Yuzde": 2.52
          },
          {
            "HarfNotu": "DC+",
            "Sayi": 0,
            "Yuzde": 0.0
          },
          {
            "HarfNotu": "DC",
            "Sayi": 1,
            "Yuzde": 0.84
          },
          {
            "HarfNotu": "DD+",
            "Sayi": 0,
            "Yuzde": 0.0
          },
          {
            "HarfNotu": "DD",
            "Sayi": 2,
            "Yuzde": 1.68
          },
          {
            "HarfNotu": "FF",
            "Sayi": 7,
            "Yuzde": 5.88
          },
          {
            "HarfNotu": "VF",
            "Sayi": 4,
            "Yuzde": 3.36
          }
        ]
      },
      {
        "dersNo": "101",
        "donemKodu": "202020",
        "yilAdi": "2019-2020",
        "donemTip": "Bahar Dönemi",
        "toplamOgrenci": 76,
        "dagilim": [
          {
            "HarfNotu": "AA",
            "Sayi": 30,
            "Yuzde": 39.47
          },
          {
            "HarfNotu": "BA+",
            "Sayi": 0,
            "Yuzde": 0.0
          },
          {
            "HarfNotu": "BA",
            "Sayi": 27,
            "Yuzde": 35.53
          },
          {
            "HarfNotu": "BB+",
            "Sayi": 0,
            "Yuzde": 0.0
          },
          {
            "HarfNotu": "BB",
            "Sayi": 11,
            "Yuzde": 14.47
          },
          {
            "HarfNotu": "CB+",
            "Sayi": 0,
            "Yuzde": 0.0
          },
          {
            "HarfNotu": "CB",
            "Sayi": 1,
            "Yuzde": 1.32
          },
          {
            "HarfNotu": "CC+",
            "Sayi": 0,
            "Yuzde": 0.0
          },
          {
            "HarfNotu": "CC",
            "Sayi": 0,
            "Yuzde": 0.0
          },
          {
            "HarfNotu": "DC+",
            "Sayi": 0,
            "Yuzde": 0.0
          },
          {
            "HarfNotu": "DC",
            "Sayi": 0,
            "Yuzde": 0.0
          },
          {
            "HarfNotu": "DD+",
            "Sayi": 0,
            "Yuzde": 0.0
          },
          {
            "HarfNotu": "DD",
            "Sayi": 0,
            "Yuzde": 0.0
          },
          {
            "HarfNotu": "FF",
            "Sayi": 6,
            "Yuzde": 7.89
          },
          {
            "HarfNotu": "VF",
            "Sayi": 0,
            "Yuzde": 0.0
          }
        ]
      },
      {
        "dersNo": "101",
        "donemKodu": "202010",
        "yilAdi": "2019-2020",
        "donemTip": "Güz Dönemi",
        "toplamOgrenci": 101,
        "dagilim": [
          {
            "HarfNotu": "AA",
            "Sayi": 17,
            "Yuzde": 16.83
          },
          {
            "HarfNotu": "BA+",
            "Sayi": 0,
            "Yuzde": 0.0
          },
          {
            "HarfNotu": "BA",
            "Sayi": 40,
            "Yuzde": 39.6
          },
          {
            "HarfNotu": "BB+",
            "Sayi": 0,
            "Yuzde": 0.0
          },
          {
            "HarfNotu": "BB",
            "Sayi": 10,
            "Yuzde": 9.9
          },
          {
            "HarfNotu": "CB+",
            "Sayi": 0,
            "Yuzde": 0.0
          },
          {
            "HarfNotu": "CB",
            "Sayi": 7,
            "Yuzde": 6.93
          },
          {
            "HarfNotu": "CC+",
            "Sayi": 0,
            "Yuzde": 0.0
          },
          {
            "HarfNotu": "CC",
            "Sayi": 1,
            "Yuzde": 0.99
          },
          {
            "HarfNotu": "DC+",
            "Sayi": 0,
            "Yuzde": 0.0
          },
          {
            "HarfNotu": "DC",
            "Sayi": 4,
            "Yuzde": 3.96
          },
          {
            "HarfNotu": "DD+",
            "Sayi": 0,
            "Yuzde": 0.0
          },
          {
            "HarfNotu": "DD",
            "Sayi": 5,
            "Yuzde": 4.95
          },
          {
            "HarfNotu": "FF",
            "Sayi": 6,
            "Yuzde": 5.94
          },
          {
            "HarfNotu": "VF",
            "Sayi": 5,
            "Yuzde": 4.95
          }
        ]
      },
      {
        "dersNo": "101",
        "donemKodu": "202120",
        "yilAdi": "2020-2021",
        "donemTip": "Bahar Dönemi",
        "toplamOgrenci": 164,
        "dagilim": [
          {
            "HarfNotu": "AA",
            "Sayi": 73,
            "Yuzde": 44.51
          },
          {
            "HarfNotu": "BA+",
            "Sayi": 0,
            "Yuzde": 0.0
          },
          {
            "HarfNotu": "BA",
            "Sayi": 71,
            "Yuzde": 43.29
          },
          {
            "HarfNotu": "BB+",
            "Sayi": 0,
            "Yuzde": 0.0
          },
          {
            "HarfNotu": "BB",
            "Sayi": 9,
            "Yuzde": 5.49
          },
          {
            "HarfNotu": "CB+",
            "Sayi": 0,
            "Yuzde": 0.0
          },
          {
            "HarfNotu": "CB",
            "Sayi": 2,
            "Yuzde": 1.22
          },
          {
            "HarfNotu": "CC+",
            "Sayi": 0,
            "Yuzde": 0.0
          },
          {
            "HarfNotu": "CC",
            "Sayi": 0,
            "Yuzde": 0.0
          },
          {
            "HarfNotu": "DC+",
            "Sayi": 0,
            "Yuzde": 0.0
          },
          {
            "HarfNotu": "DC",
            "Sayi": 0,
            "Yuzde": 0.0
          },
          {
            "HarfNotu": "DD+",
            "Sayi": 0,
            "Yuzde": 0.0
          },
          {
            "HarfNotu": "DD",
            "Sayi": 0,
            "Yuzde": 0.0
          },
          {
            "HarfNotu": "FF",
            "Sayi": 2,
            "Yuzde": 1.22
          },
          {
            "HarfNotu": "VF",
            "Sayi": 3,
            "Yuzde": 1.83
          }
        ]
      },
      {
        "dersNo": "101",
        "donemKodu": "202110",
        "yilAdi": "2020-2021",
        "donemTip": "Güz Dönemi",
        "toplamOgrenci": 76,
        "dagilim": [
          {
            "HarfNotu": "AA",
            "Sayi": 30,
            "Yuzde": 39.47
          },
          {
            "HarfNotu": "BA+",
            "Sayi": 0,
            "Yuzde": 0.0
          },
          {
            "HarfNotu": "BA",
            "Sayi": 32,
            "Yuzde": 42.11
          },
          {
            "HarfNotu": "BB+",
            "Sayi": 0,
            "Yuzde": 0.0
          },
          {
            "HarfNotu": "BB",
            "Sayi": 5,
            "Yuzde": 6.58
          },
          {
            "HarfNotu": "CB+",
            "Sayi": 0,
            "Yuzde": 0.0
          },
          {
            "HarfNotu": "CB",
            "Sayi": 1,
            "Yuzde": 1.32
          },
          {
            "HarfNotu": "CC+",
            "Sayi": 0,
            "Yuzde": 0.0
          },
          {
            "HarfNotu": "CC",
            "Sayi": 0,
            "Yuzde": 0.0
          },
          {
            "HarfNotu": "DC+",
            "Sayi": 0,
            "Yuzde": 0.0
          },
          {
            "HarfNotu": "DC",
            "Sayi": 0,
            "Yuzde": 0.0
          },
          {
            "HarfNotu": "DD+",
            "Sayi": 0,
            "Yuzde": 0.0
          },
          {
            "HarfNotu": "DD",
            "Sayi": 0,
            "Yuzde": 0.0
          },
          {
            "HarfNotu": "FF",
            "Sayi": 1,
            "Yuzde": 1.32
          },
          {
            "HarfNotu": "VF",
            "Sayi": 4,
            "Yuzde": 5.26
          }
        ]
      },
      {
        "dersNo": "101",
        "donemKodu": "202220",
        "yilAdi": "2021-2022",
        "donemTip": "Bahar Dönemi",
        "toplamOgrenci": 153,
        "dagilim": [
          {
            "HarfNotu": "AA",
            "Sayi": 32,
            "Yuzde": 20.92
          },
          {
            "HarfNotu": "BA+",
            "Sayi": 0,
            "Yuzde": 0.0
          },
          {
            "HarfNotu": "BA",
            "Sayi": 44,
            "Yuzde": 28.76
          },
          {
            "HarfNotu": "BB+",
            "Sayi": 0,
            "Yuzde": 0.0
          },
          {
            "HarfNotu": "BB",
            "Sayi": 26,
            "Yuzde": 16.99
          },
          {
            "HarfNotu": "CB+",
            "Sayi": 0,
            "Yuzde": 0.0
          },
          {
            "HarfNotu": "CB",
            "Sayi": 24,
            "Yuzde": 15.69
          },
          {
            "HarfNotu": "CC+",
            "Sayi": 0,
            "Yuzde": 0.0
          },
          {
            "HarfNotu": "CC",
            "Sayi": 3,
            "Yuzde": 1.96
          },
          {
            "HarfNotu": "DC+",
            "Sayi": 0,
            "Yuzde": 0.0
          },
          {
            "HarfNotu": "DC",
            "Sayi": 4,
            "Yuzde": 2.61
          },
          {
            "HarfNotu": "DD+",
            "Sayi": 0,
            "Yuzde": 0.0
          },
          {
            "HarfNotu": "DD",
            "Sayi": 3,
            "Yuzde": 1.96
          },
          {
            "HarfNotu": "FF",
            "Sayi": 14,
            "Yuzde": 9.15
          },
          {
            "HarfNotu": "VF",
            "Sayi": 0,
            "Yuzde": 0.0
          }
        ]
      },
      {
        "dersNo": "101",
        "donemKodu": "202210",
        "yilAdi": "2021-2022",
        "donemTip": "Güz Dönemi",
        "toplamOgrenci": 59,
        "dagilim": [
          {
            "HarfNotu": "AA",
            "Sayi": 9,
            "Yuzde": 15.25
          },
          {
            "HarfNotu": "BA+",
            "Sayi": 0,
            "Yuzde": 0.0
          },
          {
            "HarfNotu": "BA",
            "Sayi": 21,
            "Yuzde": 35.59
          },
          {
            "HarfNotu": "BB+",
            "Sayi": 0,
            "Yuzde": 0.0
          },
          {
            "HarfNotu": "BB",
            "Sayi": 11,
            "Yuzde": 18.64
          },
          {
            "HarfNotu": "CB+",
            "Sayi": 0,
            "Yuzde": 0.0
          },
          {
            "HarfNotu": "CB",
            "Sayi": 5,
            "Yuzde": 8.47
          },
          {
            "HarfNotu": "CC+",
            "Sayi": 0,
            "Yuzde": 0.0
          },
          {
            "HarfNotu": "CC",
            "Sayi": 2,
            "Yuzde": 3.39
          },
          {
            "HarfNotu": "DC+",
            "Sayi": 0,
            "Yuzde": 0.0
          },
          {
            "HarfNotu": "DC",
            "Sayi": 0,
            "Yuzde": 0.0
          },
          {
            "HarfNotu": "DD+",
            "Sayi": 0,
            "Yuzde": 0.0
          },
          {
            "HarfNotu": "DD",
            "Sayi": 1,
            "Yuzde": 1.69
          },
          {
            "HarfNotu": "FF",
            "Sayi": 8,
            "Yuzde": 13.56
          },
          {
            "HarfNotu": "VF",
            "Sayi": 1,
            "Yuzde": 1.69
          }
        ]
      },
      {
        "dersNo": "101",
        "donemKodu": "202320",
        "yilAdi": "2022-2023",
        "donemTip": "Bahar Dönemi",
        "toplamOgrenci": 120,
        "dagilim": [
          {
            "HarfNotu": "AA",
            "Sayi": 55,
            "Yuzde": 45.83
          },
          {
            "HarfNotu": "BA+",
            "Sayi": 0,
            "Yuzde": 0.0
          },
          {
            "HarfNotu": "BA",
            "Sayi": 39,
            "Yuzde": 32.5
          },
          {
            "HarfNotu": "BB+",
            "Sayi": 0,
            "Yuzde": 0.0
          },
          {
            "HarfNotu": "BB",
            "Sayi": 12,
            "Yuzde": 10.0
          },
          {
            "HarfNotu": "CB+",
            "Sayi": 0,
            "Yuzde": 0.0
          },
          {
            "HarfNotu": "CB",
            "Sayi": 3,
            "Yuzde": 2.5
          },
          {
            "HarfNotu": "CC+",
            "Sayi": 0,
            "Yuzde": 0.0
          },
          {
            "HarfNotu": "CC",
            "Sayi": 0,
            "Yuzde": 0.0
          },
          {
            "HarfNotu": "DC+",
            "Sayi": 0,
            "Yuzde": 0.0
          },
          {
            "HarfNotu": "DC",
            "Sayi": 2,
            "Yuzde": 1.67
          },
          {
            "HarfNotu": "DD+",
            "Sayi": 0,
            "Yuzde": 0.0
          },
          {
            "HarfNotu": "DD",
            "Sayi": 1,
            "Yuzde": 0.83
          },
          {
            "HarfNotu": "FF",
            "Sayi": 6,
            "Yuzde": 5.0
          },
          {
            "HarfNotu": "VF",
            "Sayi": 0,
            "Yuzde": 0.0
          }
        ]
      },
      {
        "dersNo": "101",
        "donemKodu": "202310",
        "yilAdi": "2022-2023",
        "donemTip": "Güz Dönemi",
        "toplamOgrenci": 124,
        "dagilim": [
          {
            "HarfNotu": "AA",
            "Sayi": 29,
            "Yuzde": 23.39
          },
          {
            "HarfNotu": "BA+",
            "Sayi": 0,
            "Yuzde": 0.0
          },
          {
            "HarfNotu": "BA",
            "Sayi": 27,
            "Yuzde": 21.77
          },
          {
            "HarfNotu": "BB+",
            "Sayi": 0,
            "Yuzde": 0.0
          },
          {
            "HarfNotu": "BB",
            "Sayi": 23,
            "Yuzde": 18.55
          },
          {
            "HarfNotu": "CB+",
            "Sayi": 0,
            "Yuzde": 0.0
          },
          {
            "HarfNotu": "CB",
            "Sayi": 24,
            "Yuzde": 19.35
          },
          {
            "HarfNotu": "CC+",
            "Sayi": 0,
            "Yuzde": 0.0
          },
          {
            "HarfNotu": "CC",
            "Sayi": 4,
            "Yuzde": 3.23
          },
          {
            "HarfNotu": "DC+",
            "Sayi": 0,
            "Yuzde": 0.0
          },
          {
            "HarfNotu": "DC",
            "Sayi": 0,
            "Yuzde": 0.0
          },
          {
            "HarfNotu": "DD+",
            "Sayi": 0,
            "Yuzde": 0.0
          },
          {
            "HarfNotu": "DD",
            "Sayi": 0,
            "Yuzde": 0.0
          },
          {
            "HarfNotu": "FF",
            "Sayi": 15,
            "Yuzde": 12.1
          },
          {
            "HarfNotu": "VF",
            "Sayi": 0,
            "Yuzde": 0.0
          }
        ]
      },
      {
        "dersNo": "101",
        "donemKodu": "202420",
        "yilAdi": "2023-2024",
        "donemTip": "Bahar Dönemi",
        "toplamOgrenci": 185,
        "dagilim": [
          {
            "HarfNotu": "AA",
            "Sayi": 51,
            "Yuzde": 27.57
          },
          {
            "HarfNotu": "BA+",
            "Sayi": 30,
            "Yuzde": 16.22
          },
          {
            "HarfNotu": "BA",
            "Sayi": 33,
            "Yuzde": 17.84
          },
          {
            "HarfNotu": "BB+",
            "Sayi": 22,
            "Yuzde": 11.89
          },
          {
            "HarfNotu": "BB",
            "Sayi": 7,
            "Yuzde": 3.78
          },
          {
            "HarfNotu": "CB+",
            "Sayi": 4,
            "Yuzde": 2.16
          },
          {
            "HarfNotu": "CB",
            "Sayi": 4,
            "Yuzde": 2.16
          },
          {
            "HarfNotu": "CC+",
            "Sayi": 6,
            "Yuzde": 3.24
          },
          {
            "HarfNotu": "CC",
            "Sayi": 7,
            "Yuzde": 3.78
          },
          {
            "HarfNotu": "DC+",
            "Sayi": 1,
            "Yuzde": 0.54
          },
          {
            "HarfNotu": "DC",
            "Sayi": 0,
            "Yuzde": 0.0
          },
          {
            "HarfNotu": "DD+",
            "Sayi": 1,
            "Yuzde": 0.54
          },
          {
            "HarfNotu": "DD",
            "Sayi": 1,
            "Yuzde": 0.54
          },
          {
            "HarfNotu": "FF",
            "Sayi": 7,
            "Yuzde": 3.78
          },
          {
            "HarfNotu": "VF",
            "Sayi": 11,
            "Yuzde": 5.95
          }
        ]
      },
      {
        "dersNo": "101",
        "donemKodu": "202410",
        "yilAdi": "2023-2024",
        "donemTip": "Güz Dönemi",
        "toplamOgrenci": 127,
        "dagilim": [
          {
            "HarfNotu": "AA",
            "Sayi": 37,
            "Yuzde": 29.13
          },
          {
            "HarfNotu": "BA+",
            "Sayi": 25,
            "Yuzde": 19.69
          },
          {
            "HarfNotu": "BA",
            "Sayi": 19,
            "Yuzde": 14.96
          },
          {
            "HarfNotu": "BB+",
            "Sayi": 19,
            "Yuzde": 14.96
          },
          {
            "HarfNotu": "BB",
            "Sayi": 7,
            "Yuzde": 5.51
          },
          {
            "HarfNotu": "CB+",
            "Sayi": 2,
            "Yuzde": 1.57
          },
          {
            "HarfNotu": "CB",
            "Sayi": 3,
            "Yuzde": 2.36
          },
          {
            "HarfNotu": "CC+",
            "Sayi": 1,
            "Yuzde": 0.79
          },
          {
            "HarfNotu": "CC",
            "Sayi": 0,
            "Yuzde": 0.0
          },
          {
            "HarfNotu": "DC+",
            "Sayi": 0,
            "Yuzde": 0.0
          },
          {
            "HarfNotu": "DC",
            "Sayi": 1,
            "Yuzde": 0.79
          },
          {
            "HarfNotu": "DD+",
            "Sayi": 0,
            "Yuzde": 0.0
          },
          {
            "HarfNotu": "DD",
            "Sayi": 0,
            "Yuzde": 0.0
          },
          {
            "HarfNotu": "FF",
            "Sayi": 7,
            "Yuzde": 5.51
          },
          {
            "HarfNotu": "VF",
            "Sayi": 6,
            "Yuzde": 4.72
          }
        ]
      },
      {
        "dersNo": "101",
        "donemKodu": "202520",
        "yilAdi": "2024-2025",
        "donemTip": "Bahar Dönemi",
        "toplamOgrenci": 215,
        "dagilim": [
          {
            "HarfNotu": "AA",
            "Sayi": 34,
            "Yuzde": 15.81
          },
          {
            "HarfNotu": "BA+",
            "Sayi": 39,
            "Yuzde": 18.14
          },
          {
            "HarfNotu": "BA",
            "Sayi": 34,
            "Yuzde": 15.81
          },
          {
            "HarfNotu": "BB+",
            "Sayi": 39,
            "Yuzde": 18.14
          },
          {
            "HarfNotu": "BB",
            "Sayi": 25,
            "Yuzde": 11.63
          },
          {
            "HarfNotu": "CB+",
            "Sayi": 13,
            "Yuzde": 6.05
          },
          {
            "HarfNotu": "CB",
            "Sayi": 7,
            "Yuzde": 3.26
          },
          {
            "HarfNotu": "CC+",
            "Sayi": 4,
            "Yuzde": 1.86
          },
          {
            "HarfNotu": "CC",
            "Sayi": 1,
            "Yuzde": 0.47
          },
          {
            "HarfNotu": "DC+",
            "Sayi": 3,
            "Yuzde": 1.4
          },
          {
            "HarfNotu": "DC",
            "Sayi": 0,
            "Yuzde": 0.0
          },
          {
            "HarfNotu": "DD+",
            "Sayi": 0,
            "Yuzde": 0.0
          },
          {
            "HarfNotu": "DD",
            "Sayi": 2,
            "Yuzde": 0.93
          },
          {
            "HarfNotu": "FF",
            "Sayi": 1,
            "Yuzde": 0.47
          },
          {
            "HarfNotu": "VF",
            "Sayi": 10,
            "Yuzde": 4.65
          }
        ]
      },
      {
        "dersNo": "101",
        "donemKodu": "202510",
        "yilAdi": "2024-2025",
        "donemTip": "Güz Dönemi",
        "toplamOgrenci": 215,
        "dagilim": [
          {
            "HarfNotu": "AA",
            "Sayi": 60,
            "Yuzde": 27.91
          },
          {
            "HarfNotu": "BA+",
            "Sayi": 32,
            "Yuzde": 14.88
          },
          {
            "HarfNotu": "BA",
            "Sayi": 39,
            "Yuzde": 18.14
          },
          {
            "HarfNotu": "BB+",
            "Sayi": 31,
            "Yuzde": 14.42
          },
          {
            "HarfNotu": "BB",
            "Sayi": 15,
            "Yuzde": 6.98
          },
          {
            "HarfNotu": "CB+",
            "Sayi": 10,
            "Yuzde": 4.65
          },
          {
            "HarfNotu": "CB",
            "Sayi": 7,
            "Yuzde": 3.26
          },
          {
            "HarfNotu": "CC+",
            "Sayi": 2,
            "Yuzde": 0.93
          },
          {
            "HarfNotu": "CC",
            "Sayi": 2,
            "Yuzde": 0.93
          },
          {
            "HarfNotu": "DC+",
            "Sayi": 1,
            "Yuzde": 0.47
          },
          {
            "HarfNotu": "DC",
            "Sayi": 1,
            "Yuzde": 0.47
          },
          {
            "HarfNotu": "DD+",
            "Sayi": 0,
            "Yuzde": 0.0
          },
          {
            "HarfNotu": "DD",
            "Sayi": 0,
            "Yuzde": 0.0
          },
          {
            "HarfNotu": "FF",
            "Sayi": 6,
            "Yuzde": 2.79
          },
          {
            "HarfNotu": "VF",
            "Sayi": 4,
            "Yuzde": 1.86
          }
        ]
      },
      {
        "dersNo": "101",
        "donemKodu": "202610",
        "yilAdi": "2025-2026",
        "donemTip": "Güz Dönemi",
        "toplamOgrenci": 199,
        "dagilim": [
          {
            "HarfNotu": "AA",
            "Sayi": 47,
            "Yuzde": 23.62
          },
          {
            "HarfNotu": "BA+",
            "Sayi": 37,
            "Yuzde": 18.59
          },
          {
            "HarfNotu": "BA",
            "Sayi": 36,
            "Yuzde": 18.09
          },
          {
            "HarfNotu": "BB+",
            "Sayi": 29,
            "Yuzde": 14.57
          },
          {
            "HarfNotu": "BB",
            "Sayi": 18,
            "Yuzde": 9.05
          },
          {
            "HarfNotu": "CB+",
            "Sayi": 6,
            "Yuzde": 3.02
          },
          {
            "HarfNotu": "CB",
            "Sayi": 4,
            "Yuzde": 2.01
          },
          {
            "HarfNotu": "CC+",
            "Sayi": 3,
            "Yuzde": 1.51
          },
          {
            "HarfNotu": "CC",
            "Sayi": 2,
            "Yuzde": 1.01
          },
          {
            "HarfNotu": "DC+",
            "Sayi": 0,
            "Yuzde": 0.0
          },
          {
            "HarfNotu": "DC",
            "Sayi": 2,
            "Yuzde": 1.01
          },
          {
            "HarfNotu": "DD+",
            "Sayi": 0,
            "Yuzde": 0.0
          },
          {
            "HarfNotu": "DD",
            "Sayi": 0,
            "Yuzde": 0.0
          },
          {
            "HarfNotu": "FF",
            "Sayi": 10,
            "Yuzde": 5.03
          },
          {
            "HarfNotu": "VF",
            "Sayi": 1,
            "Yuzde": 0.5
          }
        ]
      }
    ]
  },
  {
    "brans": "ITA",
    "dersNo": "102",
    "terms": [
      {
        "dersNo": "102",
        "donemKodu": "201930",
        "yilAdi": "2018-2019",
        "donemTip": "Yaz Dönemi",
        "toplamOgrenci": 15,
        "dagilim": [
          {
            "HarfNotu": "AA",
            "Sayi": 9,
            "Yuzde": 60.0
          },
          {
            "HarfNotu": "BA+",
            "Sayi": 0,
            "Yuzde": 0.0
          },
          {
            "HarfNotu": "BA",
            "Sayi": 3,
            "Yuzde": 20.0
          },
          {
            "HarfNotu": "BB+",
            "Sayi": 0,
            "Yuzde": 0.0
          },
          {
            "HarfNotu": "BB",
            "Sayi": 2,
            "Yuzde": 13.33
          },
          {
            "HarfNotu": "CB+",
            "Sayi": 0,
            "Yuzde": 0.0
          },
          {
            "HarfNotu": "CB",
            "Sayi": 1,
            "Yuzde": 6.67
          },
          {
            "HarfNotu": "CC+",
            "Sayi": 0,
            "Yuzde": 0.0
          },
          {
            "HarfNotu": "CC",
            "Sayi": 0,
            "Yuzde": 0.0
          },
          {
            "HarfNotu": "DC+",
            "Sayi": 0,
            "Yuzde": 0.0
          },
          {
            "HarfNotu": "DC",
            "Sayi": 0,
            "Yuzde": 0.0
          },
          {
            "HarfNotu": "DD+",
            "Sayi": 0,
            "Yuzde": 0.0
          },
          {
            "HarfNotu": "DD",
            "Sayi": 0,
            "Yuzde": 0.0
          },
          {
            "HarfNotu": "FF",
            "Sayi": 0,
            "Yuzde": 0.0
          },
          {
            "HarfNotu": "VF",
            "Sayi": 0,
            "Yuzde": 0.0
          }
        ]
      },
      {
        "dersNo": "102",
        "donemKodu": "201920",
        "yilAdi": "2018-2019",
        "donemTip": "Bahar Dönemi",
        "toplamOgrenci": 53,
        "dagilim": [
          {
            "HarfNotu": "AA",
            "Sayi": 9,
            "Yuzde": 16.98
          },
          {
            "HarfNotu": "BA+",
            "Sayi": 0,
            "Yuzde": 0.0
          },
          {
            "HarfNotu": "BA",
            "Sayi": 15,
            "Yuzde": 28.3
          },
          {
            "HarfNotu": "BB+",
            "Sayi": 0,
            "Yuzde": 0.0
          },
          {
            "HarfNotu": "BB",
            "Sayi": 11,
            "Yuzde": 20.75
          },
          {
            "HarfNotu": "CB+",
            "Sayi": 0,
            "Yuzde": 0.0
          },
          {
            "HarfNotu": "CB",
            "Sayi": 7,
            "Yuzde": 13.21
          },
          {
            "HarfNotu": "CC+",
            "Sayi": 0,
            "Yuzde": 0.0
          },
          {
            "HarfNotu": "CC",
            "Sayi": 7,
            "Yuzde": 13.21
          },
          {
            "HarfNotu": "DC+",
            "Sayi": 0,
            "Yuzde": 0.0
          },
          {
            "HarfNotu": "DC",
            "Sayi": 0,
            "Yuzde": 0.0
          },
          {
            "HarfNotu": "DD+",
            "Sayi": 0,
            "Yuzde": 0.0
          },
          {
            "HarfNotu": "DD",
            "Sayi": 3,
            "Yuzde": 5.66
          },
          {
            "HarfNotu": "FF",
            "Sayi": 0,
            "Yuzde": 0.0
          },
          {
            "HarfNotu": "VF",
            "Sayi": 0,
            "Yuzde": 0.0
          }
        ]
      },
      {
        "dersNo": "102",
        "donemKodu": "202020",
        "yilAdi": "2019-2020",
        "donemTip": "Bahar Dönemi",
        "toplamOgrenci": 70,
        "dagilim": [
          {
            "HarfNotu": "AA",
            "Sayi": 42,
            "Yuzde": 60.0
          },
          {
            "HarfNotu": "BA+",
            "Sayi": 0,
            "Yuzde": 0.0
          },
          {
            "HarfNotu": "BA",
            "Sayi": 19,
            "Yuzde": 27.14
          },
          {
            "HarfNotu": "BB+",
            "Sayi": 0,
            "Yuzde": 0.0
          },
          {
            "HarfNotu": "BB",
            "Sayi": 3,
            "Yuzde": 4.29
          },
          {
            "HarfNotu": "CB+",
            "Sayi": 0,
            "Yuzde": 0.0
          },
          {
            "HarfNotu": "CB",
            "Sayi": 1,
            "Yuzde": 1.43
          },
          {
            "HarfNotu": "CC+",
            "Sayi": 0,
            "Yuzde": 0.0
          },
          {
            "HarfNotu": "CC",
            "Sayi": 0,
            "Yuzde": 0.0
          },
          {
            "HarfNotu": "DC+",
            "Sayi": 0,
            "Yuzde": 0.0
          },
          {
            "HarfNotu": "DC",
            "Sayi": 0,
            "Yuzde": 0.0
          },
          {
            "HarfNotu": "DD+",
            "Sayi": 0,
            "Yuzde": 0.0
          },
          {
            "HarfNotu": "DD",
            "Sayi": 0,
            "Yuzde": 0.0
          },
          {
            "HarfNotu": "FF",
            "Sayi": 5,
            "Yuzde": 7.14
          },
          {
            "HarfNotu": "VF",
            "Sayi": 0,
            "Yuzde": 0.0
          }
        ]
      },
      {
        "dersNo": "102",
        "donemKodu": "202010",
        "yilAdi": "2019-2020",
        "donemTip": "Güz Dönemi",
        "toplamOgrenci": 54,
        "dagilim": [
          {
            "HarfNotu": "AA",
            "Sayi": 11,
            "Yuzde": 20.37
          },
          {
            "HarfNotu": "BA+",
            "Sayi": 0,
            "Yuzde": 0.0
          },
          {
            "HarfNotu": "BA",
            "Sayi": 17,
            "Yuzde": 31.48
          },
          {
            "HarfNotu": "BB+",
            "Sayi": 0,
            "Yuzde": 0.0
          },
          {
            "HarfNotu": "BB",
            "Sayi": 11,
            "Yuzde": 20.37
          },
          {
            "HarfNotu": "CB+",
            "Sayi": 0,
            "Yuzde": 0.0
          },
          {
            "HarfNotu": "CB",
            "Sayi": 8,
            "Yuzde": 14.81
          },
          {
            "HarfNotu": "CC+",
            "Sayi": 0,
            "Yuzde": 0.0
          },
          {
            "HarfNotu": "CC",
            "Sayi": 0,
            "Yuzde": 0.0
          },
          {
            "HarfNotu": "DC+",
            "Sayi": 0,
            "Yuzde": 0.0
          },
          {
            "HarfNotu": "DC",
            "Sayi": 2,
            "Yuzde": 3.7
          },
          {
            "HarfNotu": "DD+",
            "Sayi": 0,
            "Yuzde": 0.0
          },
          {
            "HarfNotu": "DD",
            "Sayi": 0,
            "Yuzde": 0.0
          },
          {
            "HarfNotu": "FF",
            "Sayi": 0,
            "Yuzde": 0.0
          },
          {
            "HarfNotu": "VF",
            "Sayi": 2,
            "Yuzde": 3.7
          }
        ]
      },
      {
        "dersNo": "102",
        "donemKodu": "202120",
        "yilAdi": "2020-2021",
        "donemTip": "Bahar Dönemi",
        "toplamOgrenci": 42,
        "dagilim": [
          {
            "HarfNotu": "AA",
            "Sayi": 14,
            "Yuzde": 33.33
          },
          {
            "HarfNotu": "BA+",
            "Sayi": 0,
            "Yuzde": 0.0
          },
          {
            "HarfNotu": "BA",
            "Sayi": 17,
            "Yuzde": 40.48
          },
          {
            "HarfNotu": "BB+",
            "Sayi": 0,
            "Yuzde": 0.0
          },
          {
            "HarfNotu": "BB",
            "Sayi": 4,
            "Yuzde": 9.52
          },
          {
            "HarfNotu": "CB+",
            "Sayi": 0,
            "Yuzde": 0.0
          },
          {
            "HarfNotu": "CB",
            "Sayi": 0,
            "Yuzde": 0.0
          },
          {
            "HarfNotu": "CC+",
            "Sayi": 0,
            "Yuzde": 0.0
          },
          {
            "HarfNotu": "CC",
            "Sayi": 0,
            "Yuzde": 0.0
          },
          {
            "HarfNotu": "DC+",
            "Sayi": 0,
            "Yuzde": 0.0
          },
          {
            "HarfNotu": "DC",
            "Sayi": 0,
            "Yuzde": 0.0
          },
          {
            "HarfNotu": "DD+",
            "Sayi": 0,
            "Yuzde": 0.0
          },
          {
            "HarfNotu": "DD",
            "Sayi": 0,
            "Yuzde": 0.0
          },
          {
            "HarfNotu": "FF",
            "Sayi": 0,
            "Yuzde": 0.0
          },
          {
            "HarfNotu": "VF",
            "Sayi": 6,
            "Yuzde": 14.29
          }
        ]
      },
      {
        "dersNo": "102",
        "donemKodu": "202110",
        "yilAdi": "2020-2021",
        "donemTip": "Güz Dönemi",
        "toplamOgrenci": 38,
        "dagilim": [
          {
            "HarfNotu": "AA",
            "Sayi": 14,
            "Yuzde": 36.84
          },
          {
            "HarfNotu": "BA+",
            "Sayi": 0,
            "Yuzde": 0.0
          },
          {
            "HarfNotu": "BA",
            "Sayi": 18,
            "Yuzde": 47.37
          },
          {
            "HarfNotu": "BB+",
            "Sayi": 0,
            "Yuzde": 0.0
          },
          {
            "HarfNotu": "BB",
            "Sayi": 3,
            "Yuzde": 7.89
          },
          {
            "HarfNotu": "CB+",
            "Sayi": 0,
            "Yuzde": 0.0
          },
          {
            "HarfNotu": "CB",
            "Sayi": 0,
            "Yuzde": 0.0
          },
          {
            "HarfNotu": "CC+",
            "Sayi": 0,
            "Yuzde": 0.0
          },
          {
            "HarfNotu": "CC",
            "Sayi": 0,
            "Yuzde": 0.0
          },
          {
            "HarfNotu": "DC+",
            "Sayi": 0,
            "Yuzde": 0.0
          },
          {
            "HarfNotu": "DC",
            "Sayi": 0,
            "Yuzde": 0.0
          },
          {
            "HarfNotu": "DD+",
            "Sayi": 0,
            "Yuzde": 0.0
          },
          {
            "HarfNotu": "DD",
            "Sayi": 0,
            "Yuzde": 0.0
          },
          {
            "HarfNotu": "FF",
            "Sayi": 1,
            "Yuzde": 2.63
          },
          {
            "HarfNotu": "VF",
            "Sayi": 1,
            "Yuzde": 2.63
          }
        ]
      },
      {
        "dersNo": "102",
        "donemKodu": "202220",
        "yilAdi": "2021-2022",
        "donemTip": "Bahar Dönemi",
        "toplamOgrenci": 44,
        "dagilim": [
          {
            "HarfNotu": "AA",
            "Sayi": 4,
            "Yuzde": 9.09
          },
          {
            "HarfNotu": "BA+",
            "Sayi": 0,
            "Yuzde": 0.0
          },
          {
            "HarfNotu": "BA",
            "Sayi": 9,
            "Yuzde": 20.45
          },
          {
            "HarfNotu": "BB+",
            "Sayi": 0,
            "Yuzde": 0.0
          },
          {
            "HarfNotu": "BB",
            "Sayi": 12,
            "Yuzde": 27.27
          },
          {
            "HarfNotu": "CB+",
            "Sayi": 0,
            "Yuzde": 0.0
          },
          {
            "HarfNotu": "CB",
            "Sayi": 6,
            "Yuzde": 13.64
          },
          {
            "HarfNotu": "CC+",
            "Sayi": 0,
            "Yuzde": 0.0
          },
          {
            "HarfNotu": "CC",
            "Sayi": 4,
            "Yuzde": 9.09
          },
          {
            "HarfNotu": "DC+",
            "Sayi": 0,
            "Yuzde": 0.0
          },
          {
            "HarfNotu": "DC",
            "Sayi": 0,
            "Yuzde": 0.0
          },
          {
            "HarfNotu": "DD+",
            "Sayi": 0,
            "Yuzde": 0.0
          },
          {
            "HarfNotu": "DD",
            "Sayi": 1,
            "Yuzde": 2.27
          },
          {
            "HarfNotu": "FF",
            "Sayi": 8,
            "Yuzde": 18.18
          },
          {
            "HarfNotu": "VF",
            "Sayi": 0,
            "Yuzde": 0.0
          }
        ]
      },
      {
        "dersNo": "102",
        "donemKodu": "202210",
        "yilAdi": "2021-2022",
        "donemTip": "Güz Dönemi",
        "toplamOgrenci": 61,
        "dagilim": [
          {
            "HarfNotu": "AA",
            "Sayi": 4,
            "Yuzde": 6.56
          },
          {
            "HarfNotu": "BA+",
            "Sayi": 0,
            "Yuzde": 0.0
          },
          {
            "HarfNotu": "BA",
            "Sayi": 16,
            "Yuzde": 26.23
          },
          {
            "HarfNotu": "BB+",
            "Sayi": 0,
            "Yuzde": 0.0
          },
          {
            "HarfNotu": "BB",
            "Sayi": 9,
            "Yuzde": 14.75
          },
          {
            "HarfNotu": "CB+",
            "Sayi": 0,
            "Yuzde": 0.0
          },
          {
            "HarfNotu": "CB",
            "Sayi": 14,
            "Yuzde": 22.95
          },
          {
            "HarfNotu": "CC+",
            "Sayi": 0,
            "Yuzde": 0.0
          },
          {
            "HarfNotu": "CC",
            "Sayi": 4,
            "Yuzde": 6.56
          },
          {
            "HarfNotu": "DC+",
            "Sayi": 0,
            "Yuzde": 0.0
          },
          {
            "HarfNotu": "DC",
            "Sayi": 2,
            "Yuzde": 3.28
          },
          {
            "HarfNotu": "DD+",
            "Sayi": 0,
            "Yuzde": 0.0
          },
          {
            "HarfNotu": "DD",
            "Sayi": 2,
            "Yuzde": 3.28
          },
          {
            "HarfNotu": "FF",
            "Sayi": 5,
            "Yuzde": 8.2
          },
          {
            "HarfNotu": "VF",
            "Sayi": 3,
            "Yuzde": 4.92
          }
        ]
      },
      {
        "dersNo": "102",
        "donemKodu": "202320",
        "yilAdi": "2022-2023",
        "donemTip": "Bahar Dönemi",
        "toplamOgrenci": 60,
        "dagilim": [
          {
            "HarfNotu": "AA",
            "Sayi": 29,
            "Yuzde": 48.33
          },
          {
            "HarfNotu": "BA+",
            "Sayi": 0,
            "Yuzde": 0.0
          },
          {
            "HarfNotu": "BA",
            "Sayi": 15,
            "Yuzde": 25.0
          },
          {
            "HarfNotu": "BB+",
            "Sayi": 0,
            "Yuzde": 0.0
          },
          {
            "HarfNotu": "BB",
            "Sayi": 7,
            "Yuzde": 11.67
          },
          {
            "HarfNotu": "CB+",
            "Sayi": 0,
            "Yuzde": 0.0
          },
          {
            "HarfNotu": "CB",
            "Sayi": 1,
            "Yuzde": 1.67
          },
          {
            "HarfNotu": "CC+",
            "Sayi": 0,
            "Yuzde": 0.0
          },
          {
            "HarfNotu": "CC",
            "Sayi": 2,
            "Yuzde": 3.33
          },
          {
            "HarfNotu": "DC+",
            "Sayi": 0,
            "Yuzde": 0.0
          },
          {
            "HarfNotu": "DC",
            "Sayi": 1,
            "Yuzde": 1.67
          },
          {
            "HarfNotu": "DD+",
            "Sayi": 0,
            "Yuzde": 0.0
          },
          {
            "HarfNotu": "DD",
            "Sayi": 2,
            "Yuzde": 3.33
          },
          {
            "HarfNotu": "FF",
            "Sayi": 2,
            "Yuzde": 3.33
          },
          {
            "HarfNotu": "VF",
            "Sayi": 0,
            "Yuzde": 0.0
          }
        ]
      },
      {
        "dersNo": "102",
        "donemKodu": "202310",
        "yilAdi": "2022-2023",
        "donemTip": "Güz Dönemi",
        "toplamOgrenci": 18,
        "dagilim": [
          {
            "HarfNotu": "AA",
            "Sayi": 2,
            "Yuzde": 11.11
          },
          {
            "HarfNotu": "BA+",
            "Sayi": 0,
            "Yuzde": 0.0
          },
          {
            "HarfNotu": "BA",
            "Sayi": 5,
            "Yuzde": 27.78
          },
          {
            "HarfNotu": "BB+",
            "Sayi": 0,
            "Yuzde": 0.0
          },
          {
            "HarfNotu": "BB",
            "Sayi": 3,
            "Yuzde": 16.67
          },
          {
            "HarfNotu": "CB+",
            "Sayi": 0,
            "Yuzde": 0.0
          },
          {
            "HarfNotu": "CB",
            "Sayi": 2,
            "Yuzde": 11.11
          },
          {
            "HarfNotu": "CC+",
            "Sayi": 0,
            "Yuzde": 0.0
          },
          {
            "HarfNotu": "CC",
            "Sayi": 0,
            "Yuzde": 0.0
          },
          {
            "HarfNotu": "DC+",
            "Sayi": 0,
            "Yuzde": 0.0
          },
          {
            "HarfNotu": "DC",
            "Sayi": 1,
            "Yuzde": 5.56
          },
          {
            "HarfNotu": "DD+",
            "Sayi": 0,
            "Yuzde": 0.0
          },
          {
            "HarfNotu": "DD",
            "Sayi": 0,
            "Yuzde": 0.0
          },
          {
            "HarfNotu": "FF",
            "Sayi": 5,
            "Yuzde": 27.78
          },
          {
            "HarfNotu": "VF",
            "Sayi": 0,
            "Yuzde": 0.0
          }
        ]
      },
      {
        "dersNo": "102",
        "donemKodu": "202420",
        "yilAdi": "2023-2024",
        "donemTip": "Bahar Dönemi",
        "toplamOgrenci": 71,
        "dagilim": [
          {
            "HarfNotu": "AA",
            "Sayi": 17,
            "Yuzde": 23.94
          },
          {
            "HarfNotu": "BA+",
            "Sayi": 7,
            "Yuzde": 9.86
          },
          {
            "HarfNotu": "BA",
            "Sayi": 16,
            "Yuzde": 22.54
          },
          {
            "HarfNotu": "BB+",
            "Sayi": 7,
            "Yuzde": 9.86
          },
          {
            "HarfNotu": "BB",
            "Sayi": 5,
            "Yuzde": 7.04
          },
          {
            "HarfNotu": "CB+",
            "Sayi": 5,
            "Yuzde": 7.04
          },
          {
            "HarfNotu": "CB",
            "Sayi": 2,
            "Yuzde": 2.82
          },
          {
            "HarfNotu": "CC+",
            "Sayi": 1,
            "Yuzde": 1.41
          },
          {
            "HarfNotu": "CC",
            "Sayi": 3,
            "Yuzde": 4.23
          },
          {
            "HarfNotu": "DC+",
            "Sayi": 0,
            "Yuzde": 0.0
          },
          {
            "HarfNotu": "DC",
            "Sayi": 1,
            "Yuzde": 1.41
          },
          {
            "HarfNotu": "DD+",
            "Sayi": 0,
            "Yuzde": 0.0
          },
          {
            "HarfNotu": "DD",
            "Sayi": 0,
            "Yuzde": 0.0
          },
          {
            "HarfNotu": "FF",
            "Sayi": 1,
            "Yuzde": 1.41
          },
          {
            "HarfNotu": "VF",
            "Sayi": 6,
            "Yuzde": 8.45
          }
        ]
      },
      {
        "dersNo": "102",
        "donemKodu": "202410",
        "yilAdi": "2023-2024",
        "donemTip": "Güz Dönemi",
        "toplamOgrenci": 28,
        "dagilim": [
          {
            "HarfNotu": "AA",
            "Sayi": 5,
            "Yuzde": 17.86
          },
          {
            "HarfNotu": "BA+",
            "Sayi": 7,
            "Yuzde": 25.0
          },
          {
            "HarfNotu": "BA",
            "Sayi": 1,
            "Yuzde": 3.57
          },
          {
            "HarfNotu": "BB+",
            "Sayi": 4,
            "Yuzde": 14.29
          },
          {
            "HarfNotu": "BB",
            "Sayi": 3,
            "Yuzde": 10.71
          },
          {
            "HarfNotu": "CB+",
            "Sayi": 1,
            "Yuzde": 3.57
          },
          {
            "HarfNotu": "CB",
            "Sayi": 0,
            "Yuzde": 0.0
          },
          {
            "HarfNotu": "CC+",
            "Sayi": 1,
            "Yuzde": 3.57
          },
          {
            "HarfNotu": "CC",
            "Sayi": 0,
            "Yuzde": 0.0
          },
          {
            "HarfNotu": "DC+",
            "Sayi": 0,
            "Yuzde": 0.0
          },
          {
            "HarfNotu": "DC",
            "Sayi": 1,
            "Yuzde": 3.57
          },
          {
            "HarfNotu": "DD+",
            "Sayi": 0,
            "Yuzde": 0.0
          },
          {
            "HarfNotu": "DD",
            "Sayi": 0,
            "Yuzde": 0.0
          },
          {
            "HarfNotu": "FF",
            "Sayi": 2,
            "Yuzde": 7.14
          },
          {
            "HarfNotu": "VF",
            "Sayi": 3,
            "Yuzde": 10.71
          }
        ]
      },
      {
        "dersNo": "102",
        "donemKodu": "202520",
        "yilAdi": "2024-2025",
        "donemTip": "Bahar Dönemi",
        "toplamOgrenci": 81,
        "dagilim": [
          {
            "HarfNotu": "AA",
            "Sayi": 22,
            "Yuzde": 27.16
          },
          {
            "HarfNotu": "BA+",
            "Sayi": 12,
            "Yuzde": 14.81
          },
          {
            "HarfNotu": "BA",
            "Sayi": 10,
            "Yuzde": 12.35
          },
          {
            "HarfNotu": "BB+",
            "Sayi": 9,
            "Yuzde": 11.11
          },
          {
            "HarfNotu": "BB",
            "Sayi": 10,
            "Yuzde": 12.35
          },
          {
            "HarfNotu": "CB+",
            "Sayi": 1,
            "Yuzde": 1.23
          },
          {
            "HarfNotu": "CB",
            "Sayi": 1,
            "Yuzde": 1.23
          },
          {
            "HarfNotu": "CC+",
            "Sayi": 3,
            "Yuzde": 3.7
          },
          {
            "HarfNotu": "CC",
            "Sayi": 0,
            "Yuzde": 0.0
          },
          {
            "HarfNotu": "DC+",
            "Sayi": 0,
            "Yuzde": 0.0
          },
          {
            "HarfNotu": "DC",
            "Sayi": 1,
            "Yuzde": 1.23
          },
          {
            "HarfNotu": "DD+",
            "Sayi": 0,
            "Yuzde": 0.0
          },
          {
            "HarfNotu": "DD",
            "Sayi": 0,
            "Yuzde": 0.0
          },
          {
            "HarfNotu": "FF",
            "Sayi": 1,
            "Yuzde": 1.23
          },
          {
            "HarfNotu": "VF",
            "Sayi": 8,
            "Yuzde": 9.88
          }
        ]
      },
      {
        "dersNo": "102",
        "donemKodu": "202510",
        "yilAdi": "2024-2025",
        "donemTip": "Güz Dönemi",
        "toplamOgrenci": 67,
        "dagilim": [
          {
            "HarfNotu": "AA",
            "Sayi": 10,
            "Yuzde": 14.93
          },
          {
            "HarfNotu": "BA+",
            "Sayi": 15,
            "Yuzde": 22.39
          },
          {
            "HarfNotu": "BA",
            "Sayi": 9,
            "Yuzde": 13.43
          },
          {
            "HarfNotu": "BB+",
            "Sayi": 8,
            "Yuzde": 11.94
          },
          {
            "HarfNotu": "BB",
            "Sayi": 3,
            "Yuzde": 4.48
          },
          {
            "HarfNotu": "CB+",
            "Sayi": 2,
            "Yuzde": 2.99
          },
          {
            "HarfNotu": "CB",
            "Sayi": 5,
            "Yuzde": 7.46
          },
          {
            "HarfNotu": "CC+",
            "Sayi": 1,
            "Yuzde": 1.49
          },
          {
            "HarfNotu": "CC",
            "Sayi": 0,
            "Yuzde": 0.0
          },
          {
            "HarfNotu": "DC+",
            "Sayi": 0,
            "Yuzde": 0.0
          },
          {
            "HarfNotu": "DC",
            "Sayi": 0,
            "Yuzde": 0.0
          },
          {
            "HarfNotu": "DD+",
            "Sayi": 0,
            "Yuzde": 0.0
          },
          {
            "HarfNotu": "DD",
            "Sayi": 0,
            "Yuzde": 0.0
          },
          {
            "HarfNotu": "FF",
            "Sayi": 1,
            "Yuzde": 1.49
          },
          {
            "HarfNotu": "VF",
            "Sayi": 8,
            "Yuzde": 11.94
          }
        ]
      },
      {
        "dersNo": "102",
        "donemKodu": "202610",
        "yilAdi": "2025-2026",
        "donemTip": "Güz Dönemi",
        "toplamOgrenci": 34,
        "dagilim": [
          {
            "HarfNotu": "AA",
            "Sayi": 6,
            "Yuzde": 17.65
          },
          {
            "HarfNotu": "BA+",
            "Sayi": 8,
            "Yuzde": 23.53
          },
          {
            "HarfNotu": "BA",
            "Sayi": 8,
            "Yuzde": 23.53
          },
          {
            "HarfNotu": "BB+",
            "Sayi": 1,
            "Yuzde": 2.94
          },
          {
            "HarfNotu": "BB",
            "Sayi": 1,
            "Yuzde": 2.94
          },
          {
            "HarfNotu": "CB+",
            "Sayi": 0,
            "Yuzde": 0.0
          },
          {
            "HarfNotu": "CB",
            "Sayi": 1,
            "Yuzde": 2.94
          },
          {
            "HarfNotu": "CC+",
            "Sayi": 1,
            "Yuzde": 2.94
          },
          {
            "HarfNotu": "CC",
            "Sayi": 0,
            "Yuzde": 0.0
          },
          {
            "HarfNotu": "DC+",
            "Sayi": 0,
            "Yuzde": 0.0
          },
          {
            "HarfNotu": "DC",
            "Sayi": 0,
            "Yuzde": 0.0
          },
          {
            "HarfNotu": "DD+",
            "Sayi": 0,
            "Yuzde": 0.0
          },
          {
            "HarfNotu": "DD",
            "Sayi": 0,
            "Yuzde": 0.0
          },
          {
            "HarfNotu": "FF",
            "Sayi": 0,
            "Yuzde": 0.0
          },
          {
            "HarfNotu": "VF",
            "Sayi": 7,
            "Yuzde": 20.59
          }
        ]
      }
    ]
  },
  {
    "brans": "ITA",
    "dersNo": "201",
    "terms": [
      {
        "dersNo": "201",
        "donemKodu": "201920",
        "yilAdi": "2018-2019",
        "donemTip": "Bahar Dönemi",
        "toplamOgrenci": 8,
        "dagilim": [
          {
            "HarfNotu": "AA",
            "Sayi": 0,
            "Yuzde": 0.0
          },
          {
            "HarfNotu": "BA+",
            "Sayi": 0,
            "Yuzde": 0.0
          },
          {
            "HarfNotu": "BA",
            "Sayi": 1,
            "Yuzde": 12.5
          },
          {
            "HarfNotu": "BB+",
            "Sayi": 0,
            "Yuzde": 0.0
          },
          {
            "HarfNotu": "BB",
            "Sayi": 1,
            "Yuzde": 12.5
          },
          {
            "HarfNotu": "CB+",
            "Sayi": 0,
            "Yuzde": 0.0
          },
          {
            "HarfNotu": "CB",
            "Sayi": 4,
            "Yuzde": 50.0
          },
          {
            "HarfNotu": "CC+",
            "Sayi": 0,
            "Yuzde": 0.0
          },
          {
            "HarfNotu": "CC",
            "Sayi": 0,
            "Yuzde": 0.0
          },
          {
            "HarfNotu": "DC+",
            "Sayi": 0,
            "Yuzde": 0.0
          },
          {
            "HarfNotu": "DC",
            "Sayi": 0,
            "Yuzde": 0.0
          },
          {
            "HarfNotu": "DD+",
            "Sayi": 0,
            "Yuzde": 0.0
          },
          {
            "HarfNotu": "DD",
            "Sayi": 0,
            "Yuzde": 0.0
          },
          {
            "HarfNotu": "FF",
            "Sayi": 2,
            "Yuzde": 25.0
          },
          {
            "HarfNotu": "VF",
            "Sayi": 0,
            "Yuzde": 0.0
          }
        ]
      },
      {
        "dersNo": "201",
        "donemKodu": "202020",
        "yilAdi": "2019-2020",
        "donemTip": "Bahar Dönemi",
        "toplamOgrenci": 29,
        "dagilim": [
          {
            "HarfNotu": "AA",
            "Sayi": 11,
            "Yuzde": 37.93
          },
          {
            "HarfNotu": "BA+",
            "Sayi": 0,
            "Yuzde": 0.0
          },
          {
            "HarfNotu": "BA",
            "Sayi": 7,
            "Yuzde": 24.14
          },
          {
            "HarfNotu": "BB+",
            "Sayi": 0,
            "Yuzde": 0.0
          },
          {
            "HarfNotu": "BB",
            "Sayi": 6,
            "Yuzde": 20.69
          },
          {
            "HarfNotu": "CB+",
            "Sayi": 0,
            "Yuzde": 0.0
          },
          {
            "HarfNotu": "CB",
            "Sayi": 2,
            "Yuzde": 6.9
          },
          {
            "HarfNotu": "CC+",
            "Sayi": 0,
            "Yuzde": 0.0
          },
          {
            "HarfNotu": "CC",
            "Sayi": 0,
            "Yuzde": 0.0
          },
          {
            "HarfNotu": "DC+",
            "Sayi": 0,
            "Yuzde": 0.0
          },
          {
            "HarfNotu": "DC",
            "Sayi": 0,
            "Yuzde": 0.0
          },
          {
            "HarfNotu": "DD+",
            "Sayi": 0,
            "Yuzde": 0.0
          },
          {
            "HarfNotu": "DD",
            "Sayi": 1,
            "Yuzde": 3.45
          },
          {
            "HarfNotu": "FF",
            "Sayi": 2,
            "Yuzde": 6.9
          },
          {
            "HarfNotu": "VF",
            "Sayi": 0,
            "Yuzde": 0.0
          }
        ]
      },
      {
        "dersNo": "201",
        "donemKodu": "202010",
        "yilAdi": "2019-2020",
        "donemTip": "Güz Dönemi",
        "toplamOgrenci": 28,
        "dagilim": [
          {
            "HarfNotu": "AA",
            "Sayi": 8,
            "Yuzde": 28.57
          },
          {
            "HarfNotu": "BA+",
            "Sayi": 0,
            "Yuzde": 0.0
          },
          {
            "HarfNotu": "BA",
            "Sayi": 10,
            "Yuzde": 35.71
          },
          {
            "HarfNotu": "BB+",
            "Sayi": 0,
            "Yuzde": 0.0
          },
          {
            "HarfNotu": "BB",
            "Sayi": 6,
            "Yuzde": 21.43
          },
          {
            "HarfNotu": "CB+",
            "Sayi": 0,
            "Yuzde": 0.0
          },
          {
            "HarfNotu": "CB",
            "Sayi": 3,
            "Yuzde": 10.71
          },
          {
            "HarfNotu": "CC+",
            "Sayi": 0,
            "Yuzde": 0.0
          },
          {
            "HarfNotu": "CC",
            "Sayi": 0,
            "Yuzde": 0.0
          },
          {
            "HarfNotu": "DC+",
            "Sayi": 0,
            "Yuzde": 0.0
          },
          {
            "HarfNotu": "DC",
            "Sayi": 0,
            "Yuzde": 0.0
          },
          {
            "HarfNotu": "DD+",
            "Sayi": 0,
            "Yuzde": 0.0
          },
          {
            "HarfNotu": "DD",
            "Sayi": 0,
            "Yuzde": 0.0
          },
          {
            "HarfNotu": "FF",
            "Sayi": 0,
            "Yuzde": 0.0
          },
          {
            "HarfNotu": "VF",
            "Sayi": 1,
            "Yuzde": 3.57
          }
        ]
      },
      {
        "dersNo": "201",
        "donemKodu": "202120",
        "yilAdi": "2020-2021",
        "donemTip": "Bahar Dönemi",
        "toplamOgrenci": 17,
        "dagilim": [
          {
            "HarfNotu": "AA",
            "Sayi": 7,
            "Yuzde": 41.18
          },
          {
            "HarfNotu": "BA+",
            "Sayi": 0,
            "Yuzde": 0.0
          },
          {
            "HarfNotu": "BA",
            "Sayi": 6,
            "Yuzde": 35.29
          },
          {
            "HarfNotu": "BB+",
            "Sayi": 0,
            "Yuzde": 0.0
          },
          {
            "HarfNotu": "BB",
            "Sayi": 1,
            "Yuzde": 5.88
          },
          {
            "HarfNotu": "CB+",
            "Sayi": 0,
            "Yuzde": 0.0
          },
          {
            "HarfNotu": "CB",
            "Sayi": 0,
            "Yuzde": 0.0
          },
          {
            "HarfNotu": "CC+",
            "Sayi": 0,
            "Yuzde": 0.0
          },
          {
            "HarfNotu": "CC",
            "Sayi": 0,
            "Yuzde": 0.0
          },
          {
            "HarfNotu": "DC+",
            "Sayi": 0,
            "Yuzde": 0.0
          },
          {
            "HarfNotu": "DC",
            "Sayi": 0,
            "Yuzde": 0.0
          },
          {
            "HarfNotu": "DD+",
            "Sayi": 0,
            "Yuzde": 0.0
          },
          {
            "HarfNotu": "DD",
            "Sayi": 0,
            "Yuzde": 0.0
          },
          {
            "HarfNotu": "FF",
            "Sayi": 0,
            "Yuzde": 0.0
          },
          {
            "HarfNotu": "VF",
            "Sayi": 2,
            "Yuzde": 11.76
          }
        ]
      },
      {
        "dersNo": "201",
        "donemKodu": "202110",
        "yilAdi": "2020-2021",
        "donemTip": "Güz Dönemi",
        "toplamOgrenci": 20,
        "dagilim": [
          {
            "HarfNotu": "AA",
            "Sayi": 8,
            "Yuzde": 40.0
          },
          {
            "HarfNotu": "BA+",
            "Sayi": 0,
            "Yuzde": 0.0
          },
          {
            "HarfNotu": "BA",
            "Sayi": 7,
            "Yuzde": 35.0
          },
          {
            "HarfNotu": "BB+",
            "Sayi": 0,
            "Yuzde": 0.0
          },
          {
            "HarfNotu": "BB",
            "Sayi": 1,
            "Yuzde": 5.0
          },
          {
            "HarfNotu": "CB+",
            "Sayi": 0,
            "Yuzde": 0.0
          },
          {
            "HarfNotu": "CB",
            "Sayi": 1,
            "Yuzde": 5.0
          },
          {
            "HarfNotu": "CC+",
            "Sayi": 0,
            "Yuzde": 0.0
          },
          {
            "HarfNotu": "CC",
            "Sayi": 0,
            "Yuzde": 0.0
          },
          {
            "HarfNotu": "DC+",
            "Sayi": 0,
            "Yuzde": 0.0
          },
          {
            "HarfNotu": "DC",
            "Sayi": 0,
            "Yuzde": 0.0
          },
          {
            "HarfNotu": "DD+",
            "Sayi": 0,
            "Yuzde": 0.0
          },
          {
            "HarfNotu": "DD",
            "Sayi": 0,
            "Yuzde": 0.0
          },
          {
            "HarfNotu": "FF",
            "Sayi": 2,
            "Yuzde": 10.0
          },
          {
            "HarfNotu": "VF",
            "Sayi": 0,
            "Yuzde": 0.0
          }
        ]
      },
      {
        "dersNo": "201",
        "donemKodu": "202220",
        "yilAdi": "2021-2022",
        "donemTip": "Bahar Dönemi",
        "toplamOgrenci": 10,
        "dagilim": [
          {
            "HarfNotu": "AA",
            "Sayi": 3,
            "Yuzde": 30.0
          },
          {
            "HarfNotu": "BA+",
            "Sayi": 0,
            "Yuzde": 0.0
          },
          {
            "HarfNotu": "BA",
            "Sayi": 0,
            "Yuzde": 0.0
          },
          {
            "HarfNotu": "BB+",
            "Sayi": 0,
            "Yuzde": 0.0
          },
          {
            "HarfNotu": "BB",
            "Sayi": 2,
            "Yuzde": 20.0
          },
          {
            "HarfNotu": "CB+",
            "Sayi": 0,
            "Yuzde": 0.0
          },
          {
            "HarfNotu": "CB",
            "Sayi": 1,
            "Yuzde": 10.0
          },
          {
            "HarfNotu": "CC+",
            "Sayi": 0,
            "Yuzde": 0.0
          },
          {
            "HarfNotu": "CC",
            "Sayi": 3,
            "Yuzde": 30.0
          },
          {
            "HarfNotu": "DC+",
            "Sayi": 0,
            "Yuzde": 0.0
          },
          {
            "HarfNotu": "DC",
            "Sayi": 1,
            "Yuzde": 10.0
          },
          {
            "HarfNotu": "DD+",
            "Sayi": 0,
            "Yuzde": 0.0
          },
          {
            "HarfNotu": "DD",
            "Sayi": 0,
            "Yuzde": 0.0
          },
          {
            "HarfNotu": "FF",
            "Sayi": 0,
            "Yuzde": 0.0
          },
          {
            "HarfNotu": "VF",
            "Sayi": 0,
            "Yuzde": 0.0
          }
        ]
      },
      {
        "dersNo": "201",
        "donemKodu": "202210",
        "yilAdi": "2021-2022",
        "donemTip": "Güz Dönemi",
        "toplamOgrenci": 16,
        "dagilim": [
          {
            "HarfNotu": "AA",
            "Sayi": 2,
            "Yuzde": 12.5
          },
          {
            "HarfNotu": "BA+",
            "Sayi": 0,
            "Yuzde": 0.0
          },
          {
            "HarfNotu": "BA",
            "Sayi": 4,
            "Yuzde": 25.0
          },
          {
            "HarfNotu": "BB+",
            "Sayi": 0,
            "Yuzde": 0.0
          },
          {
            "HarfNotu": "BB",
            "Sayi": 2,
            "Yuzde": 12.5
          },
          {
            "HarfNotu": "CB+",
            "Sayi": 0,
            "Yuzde": 0.0
          },
          {
            "HarfNotu": "CB",
            "Sayi": 2,
            "Yuzde": 12.5
          },
          {
            "HarfNotu": "CC+",
            "Sayi": 0,
            "Yuzde": 0.0
          },
          {
            "HarfNotu": "CC",
            "Sayi": 1,
            "Yuzde": 6.25
          },
          {
            "HarfNotu": "DC+",
            "Sayi": 0,
            "Yuzde": 0.0
          },
          {
            "HarfNotu": "DC",
            "Sayi": 0,
            "Yuzde": 0.0
          },
          {
            "HarfNotu": "DD+",
            "Sayi": 0,
            "Yuzde": 0.0
          },
          {
            "HarfNotu": "DD",
            "Sayi": 0,
            "Yuzde": 0.0
          },
          {
            "HarfNotu": "FF",
            "Sayi": 2,
            "Yuzde": 12.5
          },
          {
            "HarfNotu": "VF",
            "Sayi": 1,
            "Yuzde": 6.25
          }
        ]
      },
      {
        "dersNo": "201",
        "donemKodu": "202320",
        "yilAdi": "2022-2023",
        "donemTip": "Bahar Dönemi",
        "toplamOgrenci": 14,
        "dagilim": [
          {
            "HarfNotu": "AA",
            "Sayi": 3,
            "Yuzde": 21.43
          },
          {
            "HarfNotu": "BA+",
            "Sayi": 0,
            "Yuzde": 0.0
          },
          {
            "HarfNotu": "BA",
            "Sayi": 6,
            "Yuzde": 42.86
          },
          {
            "HarfNotu": "BB+",
            "Sayi": 0,
            "Yuzde": 0.0
          },
          {
            "HarfNotu": "BB",
            "Sayi": 1,
            "Yuzde": 7.14
          },
          {
            "HarfNotu": "CB+",
            "Sayi": 0,
            "Yuzde": 0.0
          },
          {
            "HarfNotu": "CB",
            "Sayi": 1,
            "Yuzde": 7.14
          },
          {
            "HarfNotu": "CC+",
            "Sayi": 0,
            "Yuzde": 0.0
          },
          {
            "HarfNotu": "CC",
            "Sayi": 0,
            "Yuzde": 0.0
          },
          {
            "HarfNotu": "DC+",
            "Sayi": 0,
            "Yuzde": 0.0
          },
          {
            "HarfNotu": "DC",
            "Sayi": 0,
            "Yuzde": 0.0
          },
          {
            "HarfNotu": "DD+",
            "Sayi": 0,
            "Yuzde": 0.0
          },
          {
            "HarfNotu": "DD",
            "Sayi": 0,
            "Yuzde": 0.0
          },
          {
            "HarfNotu": "FF",
            "Sayi": 3,
            "Yuzde": 21.43
          },
          {
            "HarfNotu": "VF",
            "Sayi": 0,
            "Yuzde": 0.0
          }
        ]
      },
      {
        "dersNo": "201",
        "donemKodu": "202310",
        "yilAdi": "2022-2023",
        "donemTip": "Güz Dönemi",
        "toplamOgrenci": 20,
        "dagilim": [
          {
            "HarfNotu": "AA",
            "Sayi": 4,
            "Yuzde": 20.0
          },
          {
            "HarfNotu": "BA+",
            "Sayi": 0,
            "Yuzde": 0.0
          },
          {
            "HarfNotu": "BA",
            "Sayi": 2,
            "Yuzde": 10.0
          },
          {
            "HarfNotu": "BB+",
            "Sayi": 0,
            "Yuzde": 0.0
          },
          {
            "HarfNotu": "BB",
            "Sayi": 2,
            "Yuzde": 10.0
          },
          {
            "HarfNotu": "CB+",
            "Sayi": 0,
            "Yuzde": 0.0
          },
          {
            "HarfNotu": "CB",
            "Sayi": 1,
            "Yuzde": 5.0
          },
          {
            "HarfNotu": "CC+",
            "Sayi": 0,
            "Yuzde": 0.0
          },
          {
            "HarfNotu": "CC",
            "Sayi": 3,
            "Yuzde": 15.0
          },
          {
            "HarfNotu": "DC+",
            "Sayi": 0,
            "Yuzde": 0.0
          },
          {
            "HarfNotu": "DC",
            "Sayi": 0,
            "Yuzde": 0.0
          },
          {
            "HarfNotu": "DD+",
            "Sayi": 0,
            "Yuzde": 0.0
          },
          {
            "HarfNotu": "DD",
            "Sayi": 0,
            "Yuzde": 0.0
          },
          {
            "HarfNotu": "FF",
            "Sayi": 5,
            "Yuzde": 25.0
          },
          {
            "HarfNotu": "VF",
            "Sayi": 0,
            "Yuzde": 0.0
          }
        ]
      },
      {
        "dersNo": "201",
        "donemKodu": "202420",
        "yilAdi": "2023-2024",
        "donemTip": "Bahar Dönemi",
        "toplamOgrenci": 2,
        "dagilim": [
          {
            "HarfNotu": "AA",
            "Sayi": 1,
            "Yuzde": 50.0
          },
          {
            "HarfNotu": "BA+",
            "Sayi": 0,
            "Yuzde": 0.0
          },
          {
            "HarfNotu": "BA",
            "Sayi": 0,
            "Yuzde": 0.0
          },
          {
            "HarfNotu": "BB+",
            "Sayi": 0,
            "Yuzde": 0.0
          },
          {
            "HarfNotu": "BB",
            "Sayi": 0,
            "Yuzde": 0.0
          },
          {
            "HarfNotu": "CB+",
            "Sayi": 0,
            "Yuzde": 0.0
          },
          {
            "HarfNotu": "CB",
            "Sayi": 0,
            "Yuzde": 0.0
          },
          {
            "HarfNotu": "CC+",
            "Sayi": 0,
            "Yuzde": 0.0
          },
          {
            "HarfNotu": "CC",
            "Sayi": 0,
            "Yuzde": 0.0
          },
          {
            "HarfNotu": "DC+",
            "Sayi": 0,
            "Yuzde": 0.0
          },
          {
            "HarfNotu": "DC",
            "Sayi": 0,
            "Yuzde": 0.0
          },
          {
            "HarfNotu": "DD+",
            "Sayi": 0,
            "Yuzde": 0.0
          },
          {
            "HarfNotu": "DD",
            "Sayi": 0,
            "Yuzde": 0.0
          },
          {
            "HarfNotu": "FF",
            "Sayi": 0,
            "Yuzde": 0.0
          },
          {
            "HarfNotu": "VF",
            "Sayi": 1,
            "Yuzde": 50.0
          }
        ]
      },
      {
        "dersNo": "201",
        "donemKodu": "202410",
        "yilAdi": "2023-2024",
        "donemTip": "Güz Dönemi",
        "toplamOgrenci": 13,
        "dagilim": [
          {
            "HarfNotu": "AA",
            "Sayi": 5,
            "Yuzde": 38.46
          },
          {
            "HarfNotu": "BA+",
            "Sayi": 1,
            "Yuzde": 7.69
          },
          {
            "HarfNotu": "BA",
            "Sayi": 0,
            "Yuzde": 0.0
          },
          {
            "HarfNotu": "BB+",
            "Sayi": 1,
            "Yuzde": 7.69
          },
          {
            "HarfNotu": "BB",
            "Sayi": 0,
            "Yuzde": 0.0
          },
          {
            "HarfNotu": "CB+",
            "Sayi": 0,
            "Yuzde": 0.0
          },
          {
            "HarfNotu": "CB",
            "Sayi": 0,
            "Yuzde": 0.0
          },
          {
            "HarfNotu": "CC+",
            "Sayi": 0,
            "Yuzde": 0.0
          },
          {
            "HarfNotu": "CC",
            "Sayi": 0,
            "Yuzde": 0.0
          },
          {
            "HarfNotu": "DC+",
            "Sayi": 1,
            "Yuzde": 7.69
          },
          {
            "HarfNotu": "DC",
            "Sayi": 0,
            "Yuzde": 0.0
          },
          {
            "HarfNotu": "DD+",
            "Sayi": 0,
            "Yuzde": 0.0
          },
          {
            "HarfNotu": "DD",
            "Sayi": 0,
            "Yuzde": 0.0
          },
          {
            "HarfNotu": "FF",
            "Sayi": 2,
            "Yuzde": 15.38
          },
          {
            "HarfNotu": "VF",
            "Sayi": 3,
            "Yuzde": 23.08
          }
        ]
      },
      {
        "dersNo": "201",
        "donemKodu": "202520",
        "yilAdi": "2024-2025",
        "donemTip": "Bahar Dönemi",
        "toplamOgrenci": 11,
        "dagilim": [
          {
            "HarfNotu": "AA",
            "Sayi": 5,
            "Yuzde": 45.45
          },
          {
            "HarfNotu": "BA+",
            "Sayi": 1,
            "Yuzde": 9.09
          },
          {
            "HarfNotu": "BA",
            "Sayi": 0,
            "Yuzde": 0.0
          },
          {
            "HarfNotu": "BB+",
            "Sayi": 0,
            "Yuzde": 0.0
          },
          {
            "HarfNotu": "BB",
            "Sayi": 1,
            "Yuzde": 9.09
          },
          {
            "HarfNotu": "CB+",
            "Sayi": 0,
            "Yuzde": 0.0
          },
          {
            "HarfNotu": "CB",
            "Sayi": 0,
            "Yuzde": 0.0
          },
          {
            "HarfNotu": "CC+",
            "Sayi": 1,
            "Yuzde": 9.09
          },
          {
            "HarfNotu": "CC",
            "Sayi": 0,
            "Yuzde": 0.0
          },
          {
            "HarfNotu": "DC+",
            "Sayi": 1,
            "Yuzde": 9.09
          },
          {
            "HarfNotu": "DC",
            "Sayi": 0,
            "Yuzde": 0.0
          },
          {
            "HarfNotu": "DD+",
            "Sayi": 0,
            "Yuzde": 0.0
          },
          {
            "HarfNotu": "DD",
            "Sayi": 0,
            "Yuzde": 0.0
          },
          {
            "HarfNotu": "FF",
            "Sayi": 1,
            "Yuzde": 9.09
          },
          {
            "HarfNotu": "VF",
            "Sayi": 1,
            "Yuzde": 9.09
          }
        ]
      },
      {
        "dersNo": "201",
        "donemKodu": "202510",
        "yilAdi": "2024-2025",
        "donemTip": "Güz Dönemi",
        "toplamOgrenci": 31,
        "dagilim": [
          {
            "HarfNotu": "AA",
            "Sayi": 10,
            "Yuzde": 32.26
          },
          {
            "HarfNotu": "BA+",
            "Sayi": 7,
            "Yuzde": 22.58
          },
          {
            "HarfNotu": "BA",
            "Sayi": 4,
            "Yuzde": 12.9
          },
          {
            "HarfNotu": "BB+",
            "Sayi": 3,
            "Yuzde": 9.68
          },
          {
            "HarfNotu": "BB",
            "Sayi": 2,
            "Yuzde": 6.45
          },
          {
            "HarfNotu": "CB+",
            "Sayi": 0,
            "Yuzde": 0.0
          },
          {
            "HarfNotu": "CB",
            "Sayi": 0,
            "Yuzde": 0.0
          },
          {
            "HarfNotu": "CC+",
            "Sayi": 0,
            "Yuzde": 0.0
          },
          {
            "HarfNotu": "CC",
            "Sayi": 0,
            "Yuzde": 0.0
          },
          {
            "HarfNotu": "DC+",
            "Sayi": 0,
            "Yuzde": 0.0
          },
          {
            "HarfNotu": "DC",
            "Sayi": 0,
            "Yuzde": 0.0
          },
          {
            "HarfNotu": "DD+",
            "Sayi": 2,
            "Yuzde": 6.45
          },
          {
            "HarfNotu": "DD",
            "Sayi": 0,
            "Yuzde": 0.0
          },
          {
            "HarfNotu": "FF",
            "Sayi": 0,
            "Yuzde": 0.0
          },
          {
            "HarfNotu": "VF",
            "Sayi": 2,
            "Yuzde": 6.45
          }
        ]
      },
      {
        "dersNo": "201",
        "donemKodu": "202610",
        "yilAdi": "2025-2026",
        "donemTip": "Güz Dönemi",
        "toplamOgrenci": 14,
        "dagilim": [
          {
            "HarfNotu": "AA",
            "Sayi": 4,
            "Yuzde": 28.57
          },
          {
            "HarfNotu": "BA+",
            "Sayi": 3,
            "Yuzde": 21.43
          },
          {
            "HarfNotu": "BA",
            "Sayi": 1,
            "Yuzde": 7.14
          },
          {
            "HarfNotu": "BB+",
            "Sayi": 1,
            "Yuzde": 7.14
          },
          {
            "HarfNotu": "BB",
            "Sayi": 3,
            "Yuzde": 21.43
          },
          {
            "HarfNotu": "CB+",
            "Sayi": 0,
            "Yuzde": 0.0
          },
          {
            "HarfNotu": "CB",
            "Sayi": 0,
            "Yuzde": 0.0
          },
          {
            "HarfNotu": "CC+",
            "Sayi": 1,
            "Yuzde": 7.14
          },
          {
            "HarfNotu": "CC",
            "Sayi": 0,
            "Yuzde": 0.0
          },
          {
            "HarfNotu": "DC+",
            "Sayi": 0,
            "Yuzde": 0.0
          },
          {
            "HarfNotu": "DC",
            "Sayi": 0,
            "Yuzde": 0.0
          },
          {
            "HarfNotu": "DD+",
            "Sayi": 0,
            "Yuzde": 0.0
          },
          {
            "HarfNotu": "DD",
            "Sayi": 0,
            "Yuzde": 0.0
          },
          {
            "HarfNotu": "FF",
            "Sayi": 0,
            "Yuzde": 0.0
          },
          {
            "HarfNotu": "VF",
            "Sayi": 1,
            "Yuzde": 7.14
          }
        ]
      }
    ]
  },
  {
    "brans": "ITA",
    "dersNo": "202",
    "terms": [
      {
        "dersNo": "202",
        "donemKodu": "201920",
        "yilAdi": "2018-2019",
        "donemTip": "Bahar Dönemi",
        "toplamOgrenci": 0,
        "dagilim": [
          {
            "HarfNotu": "AA",
            "Sayi": 0,
            "Yuzde": 0.0
          },
          {
            "HarfNotu": "BA+",
            "Sayi": 0,
            "Yuzde": 0.0
          },
          {
            "HarfNotu": "BA",
            "Sayi": 0,
            "Yuzde": 0.0
          },
          {
            "HarfNotu": "BB+",
            "Sayi": 0,
            "Yuzde": 0.0
          },
          {
            "HarfNotu": "BB",
            "Sayi": 0,
            "Yuzde": 0.0
          },
          {
            "HarfNotu": "CB+",
            "Sayi": 0,
            "Yuzde": 0.0
          },
          {
            "HarfNotu": "CB",
            "Sayi": 0,
            "Yuzde": 0.0
          },
          {
            "HarfNotu": "CC+",
            "Sayi": 0,
            "Yuzde": 0.0
          },
          {
            "HarfNotu": "CC",
            "Sayi": 0,
            "Yuzde": 0.0
          },
          {
            "HarfNotu": "DC+",
            "Sayi": 0,
            "Yuzde": 0.0
          },
          {
            "HarfNotu": "DC",
            "Sayi": 0,
            "Yuzde": 0.0
          },
          {
            "HarfNotu": "DD+",
            "Sayi": 0,
            "Yuzde": 0.0
          },
          {
            "HarfNotu": "DD",
            "Sayi": 0,
            "Yuzde": 0.0
          },
          {
            "HarfNotu": "FF",
            "Sayi": 0,
            "Yuzde": 0.0
          },
          {
            "HarfNotu": "VF",
            "Sayi": 0,
            "Yuzde": 0.0
          }
        ]
      },
      {
        "dersNo": "202",
        "donemKodu": "202020",
        "yilAdi": "2019-2020",
        "donemTip": "Bahar Dönemi",
        "toplamOgrenci": 13,
        "dagilim": [
          {
            "HarfNotu": "AA",
            "Sayi": 6,
            "Yuzde": 46.15
          },
          {
            "HarfNotu": "BA+",
            "Sayi": 0,
            "Yuzde": 0.0
          },
          {
            "HarfNotu": "BA",
            "Sayi": 6,
            "Yuzde": 46.15
          },
          {
            "HarfNotu": "BB+",
            "Sayi": 0,
            "Yuzde": 0.0
          },
          {
            "HarfNotu": "BB",
            "Sayi": 0,
            "Yuzde": 0.0
          },
          {
            "HarfNotu": "CB+",
            "Sayi": 0,
            "Yuzde": 0.0
          },
          {
            "HarfNotu": "CB",
            "Sayi": 0,
            "Yuzde": 0.0
          },
          {
            "HarfNotu": "CC+",
            "Sayi": 0,
            "Yuzde": 0.0
          },
          {
            "HarfNotu": "CC",
            "Sayi": 0,
            "Yuzde": 0.0
          },
          {
            "HarfNotu": "DC+",
            "Sayi": 0,
            "Yuzde": 0.0
          },
          {
            "HarfNotu": "DC",
            "Sayi": 0,
            "Yuzde": 0.0
          },
          {
            "HarfNotu": "DD+",
            "Sayi": 0,
            "Yuzde": 0.0
          },
          {
            "HarfNotu": "DD",
            "Sayi": 0,
            "Yuzde": 0.0
          },
          {
            "HarfNotu": "FF",
            "Sayi": 1,
            "Yuzde": 7.69
          },
          {
            "HarfNotu": "VF",
            "Sayi": 0,
            "Yuzde": 0.0
          }
        ]
      },
      {
        "dersNo": "202",
        "donemKodu": "202010",
        "yilAdi": "2019-2020",
        "donemTip": "Güz Dönemi",
        "toplamOgrenci": 18,
        "dagilim": [
          {
            "HarfNotu": "AA",
            "Sayi": 6,
            "Yuzde": 33.33
          },
          {
            "HarfNotu": "BA+",
            "Sayi": 0,
            "Yuzde": 0.0
          },
          {
            "HarfNotu": "BA",
            "Sayi": 7,
            "Yuzde": 38.89
          },
          {
            "HarfNotu": "BB+",
            "Sayi": 0,
            "Yuzde": 0.0
          },
          {
            "HarfNotu": "BB",
            "Sayi": 0,
            "Yuzde": 0.0
          },
          {
            "HarfNotu": "CB+",
            "Sayi": 0,
            "Yuzde": 0.0
          },
          {
            "HarfNotu": "CB",
            "Sayi": 3,
            "Yuzde": 16.67
          },
          {
            "HarfNotu": "CC+",
            "Sayi": 0,
            "Yuzde": 0.0
          },
          {
            "HarfNotu": "CC",
            "Sayi": 0,
            "Yuzde": 0.0
          },
          {
            "HarfNotu": "DC+",
            "Sayi": 0,
            "Yuzde": 0.0
          },
          {
            "HarfNotu": "DC",
            "Sayi": 0,
            "Yuzde": 0.0
          },
          {
            "HarfNotu": "DD+",
            "Sayi": 0,
            "Yuzde": 0.0
          },
          {
            "HarfNotu": "DD",
            "Sayi": 1,
            "Yuzde": 5.56
          },
          {
            "HarfNotu": "FF",
            "Sayi": 1,
            "Yuzde": 5.56
          },
          {
            "HarfNotu": "VF",
            "Sayi": 0,
            "Yuzde": 0.0
          }
        ]
      },
      {
        "dersNo": "202",
        "donemKodu": "202120",
        "yilAdi": "2020-2021",
        "donemTip": "Bahar Dönemi",
        "toplamOgrenci": 3,
        "dagilim": [
          {
            "HarfNotu": "AA",
            "Sayi": 2,
            "Yuzde": 66.67
          },
          {
            "HarfNotu": "BA+",
            "Sayi": 0,
            "Yuzde": 0.0
          },
          {
            "HarfNotu": "BA",
            "Sayi": 0,
            "Yuzde": 0.0
          },
          {
            "HarfNotu": "BB+",
            "Sayi": 0,
            "Yuzde": 0.0
          },
          {
            "HarfNotu": "BB",
            "Sayi": 0,
            "Yuzde": 0.0
          },
          {
            "HarfNotu": "CB+",
            "Sayi": 0,
            "Yuzde": 0.0
          },
          {
            "HarfNotu": "CB",
            "Sayi": 0,
            "Yuzde": 0.0
          },
          {
            "HarfNotu": "CC+",
            "Sayi": 0,
            "Yuzde": 0.0
          },
          {
            "HarfNotu": "CC",
            "Sayi": 0,
            "Yuzde": 0.0
          },
          {
            "HarfNotu": "DC+",
            "Sayi": 0,
            "Yuzde": 0.0
          },
          {
            "HarfNotu": "DC",
            "Sayi": 0,
            "Yuzde": 0.0
          },
          {
            "HarfNotu": "DD+",
            "Sayi": 0,
            "Yuzde": 0.0
          },
          {
            "HarfNotu": "DD",
            "Sayi": 0,
            "Yuzde": 0.0
          },
          {
            "HarfNotu": "FF",
            "Sayi": 0,
            "Yuzde": 0.0
          },
          {
            "HarfNotu": "VF",
            "Sayi": 1,
            "Yuzde": 33.33
          }
        ]
      },
      {
        "dersNo": "202",
        "donemKodu": "202110",
        "yilAdi": "2020-2021",
        "donemTip": "Güz Dönemi",
        "toplamOgrenci": 29,
        "dagilim": [
          {
            "HarfNotu": "AA",
            "Sayi": 9,
            "Yuzde": 31.03
          },
          {
            "HarfNotu": "BA+",
            "Sayi": 0,
            "Yuzde": 0.0
          },
          {
            "HarfNotu": "BA",
            "Sayi": 16,
            "Yuzde": 55.17
          },
          {
            "HarfNotu": "BB+",
            "Sayi": 0,
            "Yuzde": 0.0
          },
          {
            "HarfNotu": "BB",
            "Sayi": 4,
            "Yuzde": 13.79
          },
          {
            "HarfNotu": "CB+",
            "Sayi": 0,
            "Yuzde": 0.0
          },
          {
            "HarfNotu": "CB",
            "Sayi": 0,
            "Yuzde": 0.0
          },
          {
            "HarfNotu": "CC+",
            "Sayi": 0,
            "Yuzde": 0.0
          },
          {
            "HarfNotu": "CC",
            "Sayi": 0,
            "Yuzde": 0.0
          },
          {
            "HarfNotu": "DC+",
            "Sayi": 0,
            "Yuzde": 0.0
          },
          {
            "HarfNotu": "DC",
            "Sayi": 0,
            "Yuzde": 0.0
          },
          {
            "HarfNotu": "DD+",
            "Sayi": 0,
            "Yuzde": 0.0
          },
          {
            "HarfNotu": "DD",
            "Sayi": 0,
            "Yuzde": 0.0
          },
          {
            "HarfNotu": "FF",
            "Sayi": 0,
            "Yuzde": 0.0
          },
          {
            "HarfNotu": "VF",
            "Sayi": 0,
            "Yuzde": 0.0
          }
        ]
      },
      {
        "dersNo": "202",
        "donemKodu": "202210",
        "yilAdi": "2021-2022",
        "donemTip": "Güz Dönemi",
        "toplamOgrenci": 25,
        "dagilim": [
          {
            "HarfNotu": "AA",
            "Sayi": 5,
            "Yuzde": 20.0
          },
          {
            "HarfNotu": "BA+",
            "Sayi": 0,
            "Yuzde": 0.0
          },
          {
            "HarfNotu": "BA",
            "Sayi": 6,
            "Yuzde": 24.0
          },
          {
            "HarfNotu": "BB+",
            "Sayi": 0,
            "Yuzde": 0.0
          },
          {
            "HarfNotu": "BB",
            "Sayi": 3,
            "Yuzde": 12.0
          },
          {
            "HarfNotu": "CB+",
            "Sayi": 0,
            "Yuzde": 0.0
          },
          {
            "HarfNotu": "CB",
            "Sayi": 1,
            "Yuzde": 4.0
          },
          {
            "HarfNotu": "CC+",
            "Sayi": 0,
            "Yuzde": 0.0
          },
          {
            "HarfNotu": "CC",
            "Sayi": 1,
            "Yuzde": 4.0
          },
          {
            "HarfNotu": "DC+",
            "Sayi": 0,
            "Yuzde": 0.0
          },
          {
            "HarfNotu": "DC",
            "Sayi": 1,
            "Yuzde": 4.0
          },
          {
            "HarfNotu": "DD+",
            "Sayi": 0,
            "Yuzde": 0.0
          },
          {
            "HarfNotu": "DD",
            "Sayi": 0,
            "Yuzde": 0.0
          },
          {
            "HarfNotu": "FF",
            "Sayi": 2,
            "Yuzde": 8.0
          },
          {
            "HarfNotu": "VF",
            "Sayi": 4,
            "Yuzde": 16.0
          }
        ]
      },
      {
        "dersNo": "202",
        "donemKodu": "202320",
        "yilAdi": "2022-2023",
        "donemTip": "Bahar Dönemi",
        "toplamOgrenci": 5,
        "dagilim": [
          {
            "HarfNotu": "AA",
            "Sayi": 3,
            "Yuzde": 60.0
          },
          {
            "HarfNotu": "BA+",
            "Sayi": 0,
            "Yuzde": 0.0
          },
          {
            "HarfNotu": "BA",
            "Sayi": 1,
            "Yuzde": 20.0
          },
          {
            "HarfNotu": "BB+",
            "Sayi": 0,
            "Yuzde": 0.0
          },
          {
            "HarfNotu": "BB",
            "Sayi": 0,
            "Yuzde": 0.0
          },
          {
            "HarfNotu": "CB+",
            "Sayi": 0,
            "Yuzde": 0.0
          },
          {
            "HarfNotu": "CB",
            "Sayi": 1,
            "Yuzde": 20.0
          },
          {
            "HarfNotu": "CC+",
            "Sayi": 0,
            "Yuzde": 0.0
          },
          {
            "HarfNotu": "CC",
            "Sayi": 0,
            "Yuzde": 0.0
          },
          {
            "HarfNotu": "DC+",
            "Sayi": 0,
            "Yuzde": 0.0
          },
          {
            "HarfNotu": "DC",
            "Sayi": 0,
            "Yuzde": 0.0
          },
          {
            "HarfNotu": "DD+",
            "Sayi": 0,
            "Yuzde": 0.0
          },
          {
            "HarfNotu": "DD",
            "Sayi": 0,
            "Yuzde": 0.0
          },
          {
            "HarfNotu": "FF",
            "Sayi": 0,
            "Yuzde": 0.0
          },
          {
            "HarfNotu": "VF",
            "Sayi": 0,
            "Yuzde": 0.0
          }
        ]
      },
      {
        "dersNo": "202",
        "donemKodu": "202310",
        "yilAdi": "2022-2023",
        "donemTip": "Güz Dönemi",
        "toplamOgrenci": 13,
        "dagilim": [
          {
            "HarfNotu": "AA",
            "Sayi": 3,
            "Yuzde": 23.08
          },
          {
            "HarfNotu": "BA+",
            "Sayi": 0,
            "Yuzde": 0.0
          },
          {
            "HarfNotu": "BA",
            "Sayi": 5,
            "Yuzde": 38.46
          },
          {
            "HarfNotu": "BB+",
            "Sayi": 0,
            "Yuzde": 0.0
          },
          {
            "HarfNotu": "BB",
            "Sayi": 0,
            "Yuzde": 0.0
          },
          {
            "HarfNotu": "CB+",
            "Sayi": 0,
            "Yuzde": 0.0
          },
          {
            "HarfNotu": "CB",
            "Sayi": 0,
            "Yuzde": 0.0
          },
          {
            "HarfNotu": "CC+",
            "Sayi": 0,
            "Yuzde": 0.0
          },
          {
            "HarfNotu": "CC",
            "Sayi": 0,
            "Yuzde": 0.0
          },
          {
            "HarfNotu": "DC+",
            "Sayi": 0,
            "Yuzde": 0.0
          },
          {
            "HarfNotu": "DC",
            "Sayi": 0,
            "Yuzde": 0.0
          },
          {
            "HarfNotu": "DD+",
            "Sayi": 0,
            "Yuzde": 0.0
          },
          {
            "HarfNotu": "DD",
            "Sayi": 0,
            "Yuzde": 0.0
          },
          {
            "HarfNotu": "FF",
            "Sayi": 4,
            "Yuzde": 30.77
          },
          {
            "HarfNotu": "VF",
            "Sayi": 0,
            "Yuzde": 0.0
          }
        ]
      },
      {
        "dersNo": "202",
        "donemKodu": "202520",
        "yilAdi": "2024-2025",
        "donemTip": "Bahar Dönemi",
        "toplamOgrenci": 10,
        "dagilim": [
          {
            "HarfNotu": "AA",
            "Sayi": 2,
            "Yuzde": 20.0
          },
          {
            "HarfNotu": "BA+",
            "Sayi": 2,
            "Yuzde": 20.0
          },
          {
            "HarfNotu": "BA",
            "Sayi": 2,
            "Yuzde": 20.0
          },
          {
            "HarfNotu": "BB+",
            "Sayi": 2,
            "Yuzde": 20.0
          },
          {
            "HarfNotu": "BB",
            "Sayi": 0,
            "Yuzde": 0.0
          },
          {
            "HarfNotu": "CB+",
            "Sayi": 0,
            "Yuzde": 0.0
          },
          {
            "HarfNotu": "CB",
            "Sayi": 0,
            "Yuzde": 0.0
          },
          {
            "HarfNotu": "CC+",
            "Sayi": 0,
            "Yuzde": 0.0
          },
          {
            "HarfNotu": "CC",
            "Sayi": 0,
            "Yuzde": 0.0
          },
          {
            "HarfNotu": "DC+",
            "Sayi": 0,
            "Yuzde": 0.0
          },
          {
            "HarfNotu": "DC",
            "Sayi": 0,
            "Yuzde": 0.0
          },
          {
            "HarfNotu": "DD+",
            "Sayi": 0,
            "Yuzde": 0.0
          },
          {
            "HarfNotu": "DD",
            "Sayi": 0,
            "Yuzde": 0.0
          },
          {
            "HarfNotu": "FF",
            "Sayi": 0,
            "Yuzde": 0.0
          },
          {
            "HarfNotu": "VF",
            "Sayi": 1,
            "Yuzde": 10.0
          }
        ]
      }
    ]
  }
]